xarray_histogram/__init__.py
xarray_histogram/accessor.py
xarray_histogram/core.py
xarray_histogram/py.typed
xarray_histogram-0.2.2.dist-info/licenses/LICENSE
xarray_histogram-0.2.2.dist-info/METADATA
xarray_histogram-0.2.2.dist-info/WHEEL
xarray_histogram-0.2.2.dist-info/top_level.txt
xarray_histogram-0.2.2.dist-info/RECORD
