Metadata-Version: 2.4
Name: xarray-histogram
Version: 0.2.2
Summary: Compute histograms from XArray data.
Author-email: Clément Haëck <clement.haeck@posteo.net>
Project-URL: Source, https://github.com/Descanonge/xarray-histogram
Project-URL: Documentation, https://xarray-histogram.readthedocs.io
Classifier: Development Status :: 4 - Beta
Classifier: License :: OSI Approved :: MIT License
Classifier: Programming Language :: Python
Classifier: Programming Language :: Python :: 3 :: Only
Classifier: Programming Language :: Python :: 3.11
Classifier: Operating System :: OS Independent
Classifier: Intended Audience :: Developers
Classifier: Intended Audience :: Science/Research
Classifier: Topic :: Utilities
Requires-Python: >=3.11
License-File: LICENSE
Requires-Dist: boost-histogram
Requires-Dist: numpy
Requires-Dist: xarray
Provides-Extra: full
Requires-Dist: dask; extra == "full"
Requires-Dist: scipy; extra == "full"
Provides-Extra: dev
Requires-Dist: dask; extra == "dev"
Requires-Dist: scipy; extra == "dev"
Requires-Dist: sphinx; extra == "dev"
Requires-Dist: sphinx-book-theme; extra == "dev"
Requires-Dist: ruff; extra == "dev"
Requires-Dist: mypy>=1.5; extra == "dev"
Requires-Dist: pytest>=7.4; extra == "dev"
Requires-Dist: coverage; extra == "dev"
Requires-Dist: pytest-cov; extra == "dev"
Provides-Extra: tests
Requires-Dist: dask; extra == "tests"
Requires-Dist: scipy; extra == "tests"
Requires-Dist: pytest>=7.4; extra == "tests"
Requires-Dist: coverage; extra == "tests"
Requires-Dist: pytest-cov; extra == "tests"
Dynamic: license-file
